{
  "HALProvider": {
    "Other Devices": {
      "SPARK MAX [1]": {
        "header": {
          "open": true
        }
      }
    }
  },
  "NTProvider": {
    "types": {
      "/FMSInfo": "FMSInfo",
      "/LiveWindow/DriveSubsystem": "Subsystem",
      "/LiveWindow/PickupSubsystem": "Subsystem",
      "/LiveWindow/Ungrouped/DifferentialDrive[1]": "DifferentialDrive",
      "/LiveWindow/Ungrouped/DigitalInput[0]": "Digital Input",
      "/LiveWindow/Ungrouped/Scheduler": "Scheduler"
    }
  },
  "NetworkTables": {
    "Shuffleboard": {
      "open": true
    }
  },
  "NetworkTables View": {
    "visible": false
  }
}
